{
  "clash_nodes": 1201,
  "v2ray_nodes": 238,
  "total_nodes": 1439,
  "update_date": "2026-07-11",
  "sources": [
    "yoyapai.com",
    "clash-rs.com",
    "nodefree.me",
    "surfboard.cc"
  ],
  "source_count": 4,
  "retention_days": 3,
  "protocols": {
    "vless": 825,
    "ss": 145,
    "vmess": 70,
    "trojan": 138,
    "hysteria2": 10,
    "anytls": 2,
    "socks5": 8,
    "http": 241
  },
  "sources_status": {
    "yoyapai.com": {
      "status": "ok",
      "reason": ""
    },
    "clash-rs.com": {
      "status": "ok",
      "reason": ""
    },
    "nodefree.me": {
      "status": "ok",
      "reason": ""
    },
    "surfboard.cc": {
      "status": "ok",
      "reason": ""
    }
  }
}